momogateway/__init__.py
momogateway/momogateway.py
momogateway-0.1.2.dist-info/METADATA
momogateway-0.1.2.dist-info/WHEEL
momogateway-0.1.2.dist-info/licenses/LICENSE
momogateway-0.1.2.dist-info/RECORD
