Metadata-Version: 2.1
Name: momogateway
Version: 0.1.2
Summary: MTN MOMO Gateway - a Python package that simplifies the process of interacting with the MTN Mobile Money (MoMo) API, making it easy to create API users, generate API keys, and obtain bearer tokens for secure transactions.
Project-URL: Homepage, https://github.com/jonahgeek/python-mtn-momo-gateway
Project-URL: Bug Tracker, https://github.com/jonahgeek/python-mtn-momo-gateway/issues
Author-email: Jonathan Mwebaze <jonahgeek@gmail.com>
License-File: LICENSE
Classifier: License :: OSI Approved :: MIT License
Classifier: Operating System :: OS Independent
Classifier: Programming Language :: Python :: 3
Requires-Python: >=3.7
